mbuzz/__init__.py
mbuzz/api.py
mbuzz/config.py
mbuzz/context.py
mbuzz/cookies.py
mbuzz/client/__init__.py
mbuzz/client/conversion.py
mbuzz/client/identify.py
mbuzz/client/track.py
mbuzz/middleware/__init__.py
mbuzz/middleware/flask.py
mbuzz/utils/__init__.py
mbuzz/utils/identifier.py
mbuzz-0.7.0.dist-info/METADATA
mbuzz-0.7.0.dist-info/WHEEL
mbuzz-0.7.0.dist-info/RECORD
